MANIFEST.in
Makefile
PartialLeastSquares-1.0.4.html
README
setup.py
Examples/PLS_regression_with_supplied_X_and_Y.py
Examples/README
Examples/X_data.csv
Examples/Y_data.csv
Examples/face_images_toy_dataset.tar.gz
Examples/face_recognition_with_PLS_toy_example.py
Examples/head_pose_estimation_with_PLS_regression_toy_example.py
Examples/head_pose_images_toy_dataset.tar.gz
PartialLeastSquares/PartialLeastSquares.py
PartialLeastSquares/__init__.py
PartialLeastSquares.egg-info/PKG-INFO
PartialLeastSquares.egg-info/SOURCES.txt
PartialLeastSquares.egg-info/dependency_links.txt
PartialLeastSquares.egg-info/top_level.txt
TestPartialLeastSquares/PartialLeastSquares.py
TestPartialLeastSquares/Test.py
TestPartialLeastSquares/TestInstallationOfImageDatasets.py
TestPartialLeastSquares/TestRegressionMatrixCalculation.py
TestPartialLeastSquares/X_data.csv
TestPartialLeastSquares/Y_data.csv