Metadata-Version: 1.2
Name: PartialLeastSquares
Version: 1.0.4
Summary: A Python module for regression and classification with the Partial Least Squares algorithm
Home-page: https://engineering.purdue.edu/kak/distPLS/PartialLeastSquares-1.0.4.html
Author: Avinash Kak
Author-email: kak@purdue.edu
Maintainer: Avinash Kak
Maintainer-email: kak@purdue.edu
License: Python Software Foundation License
Download-URL: https://engineering.purdue.edu/kak/distPLS/PartialLeastSquares-1.0.4.tar.gz
Keywords: c,l,a,s,s,i,f,i,c,a,t,i,o,n,,, ,r,e,g,r,e,s,s,i,o,n,,, ,d,a,t,a, ,d,i,m,e,n,s,i,o,n,a,l,i,t,y, ,r,e,d,u,c,t,i,o,n
Platform: A
Platform: l
Platform: l
Platform:  
Platform: p
Platform: l
Platform: a
Platform: t
Platform: f
Platform: o
Platform: r
Platform: m
Platform: s
Classifier: Topic :: Scientific/Engineering :: Information Analysis
Classifier: Programming Language :: Python :: 2.7
Classifier: Programming Language :: Python :: 3.8
